pelican_nlp/__init__.py
pelican_nlp/_version.py
pelican_nlp/cli.py
pelican_nlp/config.py
pelican_nlp/main.py
pelican_nlp/Silvia_files/Opensmile/opensmile_feature_extraction.py
pelican_nlp/Silvia_files/prosogram/prosogram.py
pelican_nlp/core/__init__.py
pelican_nlp/core/audio_document.py
pelican_nlp/core/corpus.py
pelican_nlp/core/document.py
pelican_nlp/core/participant.py
pelican_nlp/extraction/__init__.py
pelican_nlp/extraction/acoustic_feature_extraction.py
pelican_nlp/extraction/distance_from_randomness.py
pelican_nlp/extraction/extract_embeddings.py
pelican_nlp/extraction/extract_logits.py
pelican_nlp/extraction/extract_perplexity.py
pelican_nlp/extraction/extract_topic_modeling.py
pelican_nlp/extraction/language_model.py
pelican_nlp/extraction/semantic_similarity.py
pelican_nlp/extraction/test_documents/test_features.csv
pelican_nlp/extraction/test_documents/wallace_1.15_3.txt
pelican_nlp/extraction/test_documents/wallace_1.1_3.txt
pelican_nlp/extraction/test_documents/wallace_1_4.txt
pelican_nlp/metrics_statistics/embeddings_metrics_statistics.py
pelican_nlp/praat/__init__.py
pelican_nlp/praat/eps_conv.praat
pelican_nlp/praat/polytonia.praat
pelican_nlp/praat/prosogram.praat
pelican_nlp/praat/prosomain.praat
pelican_nlp/praat/prosoplot.praat
pelican_nlp/praat/segment.praat
pelican_nlp/praat/setup.praat
pelican_nlp/praat/stylize.praat
pelican_nlp/praat/util.praat
pelican_nlp/preprocessing/LPDS.py
pelican_nlp/preprocessing/__init__.py
pelican_nlp/preprocessing/pipeline.py
pelican_nlp/preprocessing/section_identificator.py
pelican_nlp/preprocessing/speaker_diarization.py
pelican_nlp/preprocessing/text_cleaner.py
pelican_nlp/preprocessing/text_importer.py
pelican_nlp/preprocessing/text_normalizer.py
pelican_nlp/preprocessing/text_tokenizer.py
pelican_nlp/preprocessing/transcription.py
pelican_nlp/sample_configuration_files/config_discourse.yml
pelican_nlp/sample_configuration_files/config_fluency.yml
pelican_nlp/sample_configuration_files/config_general.yml
pelican_nlp-0.3.24.dist-info/licenses/LICENSE
pelican_nlp-0.3.24.dist-info/METADATA
pelican_nlp-0.3.24.dist-info/WHEEL
pelican_nlp-0.3.24.dist-info/entry_points.txt
pelican_nlp-0.3.24.dist-info/top_level.txt
pelican_nlp-0.3.24.dist-info/RECORD
