Metadata-Version: 2.4
Name: pelican_nlp
Version: 0.3.24
Summary: Preprocessing and Extraction of Linguistic Information for Computational Analysis
Author-email: Yves Pauli <yves.pauli@gmail.com>
License-Expression: CC-BY-NC-4.0
Project-URL: Homepage, https://github.com/ypauli/pelican_nlp
Project-URL: Repository, https://github.com/ypauli/pelican_nlp
Project-URL: Documentation, https://github.com/ypauli/pelican_nlp#readme
Project-URL: Bug Tracker, https://github.com/ypauli/pelican_nlp/issues
Keywords: nlp,linguistics,preprocessing,language-processing,text-analysis
Classifier: Development Status :: 1 - Planning
Classifier: Intended Audience :: Science/Research
Classifier: Operating System :: POSIX :: Linux
Classifier: Programming Language :: Python :: 3
Classifier: Programming Language :: Python :: 3.10
Classifier: Natural Language :: English
Classifier: Topic :: Scientific/Engineering :: Artificial Intelligence
Classifier: Topic :: Text Processing :: Linguistic
Requires-Python: >=3.10
License-File: LICENSE
Requires-Dist: numpy==2.0.1
Requires-Dist: pandas==2.2.3
Requires-Dist: PyYAML>=6.0.2
Requires-Dist: torch==2.5.1
Requires-Dist: spacy==3.8.2
Requires-Dist: transformers==4.49.0
Requires-Dist: docx2txt>=0.9
Requires-Dist: striprtf>=0.0.28
Requires-Dist: chardet>=4.0.0
Requires-Dist: scikit_learn>=1.6.1
Requires-Dist: scipy==1.15.2
Requires-Dist: fasttext-wheel==0.9.2
Requires-Dist: matplotlib>=3.10.0
Requires-Dist: seaborn>=0.13.2
Requires-Dist: accelerate==1.4.0
Requires-Dist: editdistance>=0.8.1
Requires-Dist: psutil>=6.1.0
Requires-Dist: tqdm==4.67.1
Requires-Dist: pytest>=8.3.4
Requires-Dist: statsmodels>=0.14.4
Requires-Dist: datasets==3.3.2
Requires-Dist: huggingface_hub==0.29.2
Requires-Dist: audiofile>=1.5.1
Requires-Dist: soundfile>=0.13.1
Requires-Dist: opensmile>=2.6.0
Requires-Dist: praat-parselmouth>=0.4.6
Requires-Dist: librosa>=0.10.0
Requires-Dist: pydub>=0.25.1
Requires-Dist: torchaudio>=2.5.1
Requires-Dist: pyannote.audio>=3.1.0
Requires-Dist: uroman>=0.1.0
Requires-Dist: PyPDF2>=3.0.1
Requires-Dist: ortools>=9.10.0
Requires-Dist: sentence-transformers>=2.7.0
Dynamic: license-file
